<?xml version="1.0" encoding="utf-8"?>
<SdkMessageProcessingStep Name="Dqt.Dynamics.plugins.AutoFill.AutoFillAttributePlugin: Create of dfeta_qualification" SdkMessageProcessingStepId="{3278de8c-ae3b-eb11-a813-000d3ab3d5b4}" xmlns:xsi="http://www.w3.org/2001/XMLSchema-instance">
  <SdkMessageId>9ebdbb1b-ea3e-db11-86a7-000a3a5473e8</SdkMessageId>
  <PluginTypeName>Dqt.Dynamics.plugins.AutoFill.AutoFillAttributePlugin, Dqt.Dynamics, Version=1.0.0.0, Culture=neutral, PublicKeyToken=1cabf3a9eed1c837</PluginTypeName>
  <PluginTypeId>60bdc44b-04c9-431e-947a-aa254ba0c198</PluginTypeId>
  <PrimaryEntity>dfeta_qualification</PrimaryEntity>
  <AsyncAutoDelete>0</AsyncAutoDelete>
  <Configuration>&lt;!-- dfeta_qualification config --&gt;
&lt;AutoFillPluginConfiguration xmlns:xsi='http://www.w3.org/2001/XMLSchema-instance' xmlns:xsd='http://www.w3.org/2001/XMLSchema'&gt;
  &lt;InputAttributes&gt;
    &lt;Attribute xsi:type="DateTimeAttribute" name="dfeta_he_completiondate" /&gt;
    &lt;Attribute xsi:type="DateTimeAttribute" name="dfeta_npqh_date" /&gt;
    &lt;Attribute xsi:type="DateTimeAttribute" name="dfeta_mq_date" /&gt;
    &lt;Attribute xsi:type="DateTimeAttribute" name="dfeta_hlta_assessmentdate" /&gt;
    &lt;Attribute xsi:type="DateTimeAttribute" name="dfeta_npqml_date" /&gt;
    &lt;Attribute xsi:type="DateTimeAttribute" name="dfeta_npqsl_date" /&gt;
    &lt;Attribute xsi:type="DateTimeAttribute" name="dfeta_npqel_date" /&gt;
    &lt;Attribute xsi:type="DateTimeAttribute" name="dfeta_npqlbc_date" /&gt;
    &lt;Attribute xsi:type="DateTimeAttribute" name="dfeta_npqlt_date" /&gt;
    &lt;Attribute xsi:type="DateTimeAttribute" name="dfeta_npqltd_date" /&gt;
    &lt;Attribute xsi:type="DateTimeAttribute" name="dfeta_npqll_date" /&gt;
    &lt;Attribute xsi:type="DateTimeAttribute" name="dfeta_npqeyl_date" /&gt;
  &lt;/InputAttributes&gt;
  &lt;OutputAttribute xsi:type='DateTimeAttribute' name='dfeta_completionorawarddate' /&gt;
&lt;/AutoFillPluginConfiguration&gt;</Configuration>
  <Description>Dqt.Dynamics.plugins.AutoFill.AutoFillAttributePlugin: Create of dfeta_qualification</Description>
  <FilteringAttributes></FilteringAttributes>
  <InvocationSource>1</InvocationSource>
  <Mode>0</Mode>
  <Rank>1</Rank>
  <EventHandlerTypeCode>4602</EventHandlerTypeCode>
  <Stage>20</Stage>
  <IsCustomizable>1</IsCustomizable>
  <IsHidden>0</IsHidden>
  <SupportedDeployment>0</SupportedDeployment>
  <IntroducedVersion>1.0</IntroducedVersion>
  <SdkMessageProcessingStepImages />
</SdkMessageProcessingStep>