<?xml version="1.0" encoding="utf-8"?>
<EntityRelationships xmlns:xsi="http://www.w3.org/2001/XMLSchema-instance">
  <EntityRelationship Name="account_primary_contact" unmodified="1">
    <EntityRelationshipType>OneToMany</EntityRelationshipType>
    <IntroducedVersion>5.0.0.0</IntroducedVersion>
    <IsHierarchical>0</IsHierarchical>
    <ReferencingEntityName>Account</ReferencingEntityName>
    <ReferencedEntityName>Contact</ReferencedEntityName>
    <CascadeAssign>NoCascade</CascadeAssign>
    <CascadeDelete>RemoveLink</CascadeDelete>
    <CascadeReparent>NoCascade</CascadeReparent>
    <CascadeShare>NoCascade</CascadeShare>
    <CascadeUnshare>NoCascade</CascadeUnshare>
    <CascadeRollupView>NoCascade</CascadeRollupView>
    <ReferencingAttributeName>PrimaryContactId</ReferencingAttributeName>
    <RelationshipDescription>
      <Descriptions>
        <Description description="Choose the primary contact for the account to provide quick access to contact details." languagecode="1033" />
      </Descriptions>
    </RelationshipDescription>
  </EntityRelationship>
  <EntityRelationship Name="contact_as_primary_contact">
    <EntityRelationshipType>OneToMany</EntityRelationshipType>
    <IntroducedVersion>6.1.0.0</IntroducedVersion>
    <IsHierarchical>0</IsHierarchical>
    <ReferencingEntityName>Incident</ReferencingEntityName>
    <ReferencedEntityName>Contact</ReferencedEntityName>
    <CascadeAssign>NoCascade</CascadeAssign>
    <CascadeDelete>RemoveLink</CascadeDelete>
    <CascadeReparent>NoCascade</CascadeReparent>
    <CascadeShare>NoCascade</CascadeShare>
    <CascadeUnshare>NoCascade</CascadeUnshare>
    <CascadeRollupView>NoCascade</CascadeRollupView>
    <ReferencingAttributeName>PrimaryContactId</ReferencingAttributeName>
    <RelationshipDescription>
      <Descriptions>
        <Description description="Select a primary contact for this case." languagecode="1033" />
      </Descriptions>
    </RelationshipDescription>
  </EntityRelationship>
  <EntityRelationship Name="contact_as_responsible_contact">
    <EntityRelationshipType>OneToMany</EntityRelationshipType>
    <IntroducedVersion>5.0.0.0</IntroducedVersion>
    <IsHierarchical>0</IsHierarchical>
    <ReferencingEntityName>Incident</ReferencingEntityName>
    <ReferencedEntityName>Contact</ReferencedEntityName>
    <CascadeAssign>NoCascade</CascadeAssign>
    <CascadeDelete>RemoveLink</CascadeDelete>
    <CascadeReparent>NoCascade</CascadeReparent>
    <CascadeShare>NoCascade</CascadeShare>
    <CascadeUnshare>NoCascade</CascadeUnshare>
    <CascadeRollupView>NoCascade</CascadeRollupView>
    <ReferencingAttributeName>ResponsibleContactId</ReferencingAttributeName>
    <RelationshipDescription>
      <Descriptions>
        <Description description="Choose an additional customer contact who can also help resolve the case." languagecode="1033" />
      </Descriptions>
    </RelationshipDescription>
  </EntityRelationship>
  <EntityRelationship Name="contact_master_contact" unmodified="1">
    <EntityRelationshipType>OneToMany</EntityRelationshipType>
    <IntroducedVersion>5.0.0.0</IntroducedVersion>
    <IsHierarchical>0</IsHierarchical>
    <ReferencingEntityName>Contact</ReferencingEntityName>
    <ReferencedEntityName>Contact</ReferencedEntityName>
    <CascadeAssign>NoCascade</CascadeAssign>
    <CascadeDelete>RemoveLink</CascadeDelete>
    <CascadeReparent>NoCascade</CascadeReparent>
    <CascadeShare>NoCascade</CascadeShare>
    <CascadeUnshare>NoCascade</CascadeUnshare>
    <CascadeRollupView>NoCascade</CascadeRollupView>
    <ReferencingAttributeName>MasterId</ReferencingAttributeName>
    <RelationshipDescription>
      <Descriptions>
        <Description description="Unique identifier of the master contact for merge." languagecode="1033" />
      </Descriptions>
    </RelationshipDescription>
  </EntityRelationship>
  <EntityRelationship Name="Contact_Tasks" unmodified="1">
    <EntityRelationshipType>OneToMany</EntityRelationshipType>
    <IntroducedVersion>5.0.0.0</IntroducedVersion>
    <IsHierarchical>0</IsHierarchical>
    <ReferencingEntityName>Task</ReferencingEntityName>
    <ReferencedEntityName>Contact</ReferencedEntityName>
    <CascadeAssign>Cascade</CascadeAssign>
    <CascadeDelete>Cascade</CascadeDelete>
    <CascadeReparent>Cascade</CascadeReparent>
    <CascadeShare>Cascade</CascadeShare>
    <CascadeUnshare>Cascade</CascadeUnshare>
    <CascadeRollupView>NoCascade</CascadeRollupView>
    <ReferencingAttributeName>RegardingObjectId</ReferencingAttributeName>
    <RelationshipDescription>
      <Descriptions>
        <Description description="Unique identifier of the object with which the task is associated." languagecode="1033" />
      </Descriptions>
    </RelationshipDescription>
  </EntityRelationship>
  <EntityRelationship Name="dfeta_contact_dfeta_businesseventaudit_Person">
    <EntityRelationshipType>OneToMany</EntityRelationshipType>
    <IsCustomizable>1</IsCustomizable>
    <IntroducedVersion>1.5.1.57</IntroducedVersion>
    <IsHierarchical>0</IsHierarchical>
    <ReferencingEntityName>dfeta_businesseventaudit</ReferencingEntityName>
    <ReferencedEntityName>Contact</ReferencedEntityName>
    <CascadeAssign>NoCascade</CascadeAssign>
    <CascadeDelete>RemoveLink</CascadeDelete>
    <CascadeReparent>NoCascade</CascadeReparent>
    <CascadeShare>NoCascade</CascadeShare>
    <CascadeUnshare>NoCascade</CascadeUnshare>
    <CascadeRollupView>NoCascade</CascadeRollupView>
    <IsValidForAdvancedFind>1</IsValidForAdvancedFind>
    <ReferencingAttributeName>dfeta_Person</ReferencingAttributeName>
    <RelationshipDescription>
      <Descriptions>
        <Description description="Unique identifier for Person associated with Business Event Audit." languagecode="1033" />
      </Descriptions>
    </RelationshipDescription>
    <EntityRelationshipRoles>
      <EntityRelationshipRole>
        <NavPaneDisplayOption>UseCollectionName</NavPaneDisplayOption>
        <NavPaneArea>Details</NavPaneArea>
        <NavPaneOrder>10000</NavPaneOrder>
        <NavigationPropertyName>dfeta_person</NavigationPropertyName>
        <CustomLabels>
          <CustomLabel description="" languagecode="1033" />
        </CustomLabels>
        <RelationshipRoleType>1</RelationshipRoleType>
      </EntityRelationshipRole>
      <EntityRelationshipRole>
        <NavigationPropertyName>dfeta_contact_dfeta_businesseventaudit_Person</NavigationPropertyName>
        <RelationshipRoleType>0</RelationshipRoleType>
      </EntityRelationshipRole>
    </EntityRelationshipRoles>
  </EntityRelationship>
  <EntityRelationship Name="dfeta_contact_dfeta_confirmationletter">
    <EntityRelationshipType>OneToMany</EntityRelationshipType>
    <IsCustomizable>1</IsCustomizable>
    <IntroducedVersion>1.5.1.57</IntroducedVersion>
    <IsHierarchical>0</IsHierarchical>
    <ReferencingEntityName>dfeta_confirmationletter</ReferencingEntityName>
    <ReferencedEntityName>Contact</ReferencedEntityName>
    <CascadeAssign>Cascade</CascadeAssign>
    <CascadeDelete>Cascade</CascadeDelete>
    <CascadeReparent>Cascade</CascadeReparent>
    <CascadeShare>Cascade</CascadeShare>
    <CascadeUnshare>Cascade</CascadeUnshare>
    <CascadeRollupView>NoCascade</CascadeRollupView>
    <IsValidForAdvancedFind>1</IsValidForAdvancedFind>
    <ReferencingAttributeName>dfeta_PersonId</ReferencingAttributeName>
    <RelationshipDescription>
      <Descriptions>
        <Description description="Unique identifier for Person associated with Confirmation Letter." languagecode="1033" />
      </Descriptions>
    </RelationshipDescription>
    <EntityRelationshipRoles>
      <EntityRelationshipRole>
        <NavPaneDisplayOption>UseCollectionName</NavPaneDisplayOption>
        <NavPaneArea>Details</NavPaneArea>
        <NavPaneOrder>10000</NavPaneOrder>
        <NavigationPropertyName>dfeta_personid</NavigationPropertyName>
        <CustomLabels>
          <CustomLabel description="" languagecode="1033" />
        </CustomLabels>
        <RelationshipRoleType>1</RelationshipRoleType>
      </EntityRelationshipRole>
      <EntityRelationshipRole>
        <NavigationPropertyName>dfeta_contact_dfeta_confirmationletter</NavigationPropertyName>
        <RelationshipRoleType>0</RelationshipRoleType>
      </EntityRelationshipRole>
    </EntityRelationshipRoles>
  </EntityRelationship>
  <EntityRelationship Name="dfeta_contact_dfeta_document">
    <EntityRelationshipType>OneToMany</EntityRelationshipType>
    <IsCustomizable>1</IsCustomizable>
    <IntroducedVersion>1.5.1.57</IntroducedVersion>
    <IsHierarchical>0</IsHierarchical>
    <ReferencingEntityName>dfeta_document</ReferencingEntityName>
    <ReferencedEntityName>Contact</ReferencedEntityName>
    <CascadeAssign>Cascade</CascadeAssign>
    <CascadeDelete>Cascade</CascadeDelete>
    <CascadeReparent>Cascade</CascadeReparent>
    <CascadeShare>Cascade</CascadeShare>
    <CascadeUnshare>Cascade</CascadeUnshare>
    <CascadeRollupView>NoCascade</CascadeRollupView>
    <IsValidForAdvancedFind>1</IsValidForAdvancedFind>
    <ReferencingAttributeName>dfeta_PersonId</ReferencingAttributeName>
    <RelationshipDescription>
      <Descriptions>
        <Description description="Unique identifier for Person associated with Document." languagecode="1033" />
      </Descriptions>
    </RelationshipDescription>
    <EntityRelationshipRoles>
      <EntityRelationshipRole>
        <NavPaneDisplayOption>UseCollectionName</NavPaneDisplayOption>
        <NavPaneArea>Details</NavPaneArea>
        <NavPaneOrder>10000</NavPaneOrder>
        <NavigationPropertyName>dfeta_personid</NavigationPropertyName>
        <CustomLabels>
          <CustomLabel description="" languagecode="1033" />
        </CustomLabels>
        <RelationshipRoleType>1</RelationshipRoleType>
      </EntityRelationshipRole>
      <EntityRelationshipRole>
        <NavigationPropertyName>dfeta_contact_dfeta_document</NavigationPropertyName>
        <RelationshipRoleType>0</RelationshipRoleType>
      </EntityRelationshipRole>
    </EntityRelationshipRoles>
  </EntityRelationship>
  <EntityRelationship Name="dfeta_contact_dfeta_employment">
    <EntityRelationshipType>OneToMany</EntityRelationshipType>
    <IsCustomizable>1</IsCustomizable>
    <IntroducedVersion>1.5.1.57</IntroducedVersion>
    <IsHierarchical>0</IsHierarchical>
    <ReferencingEntityName>dfeta_employment</ReferencingEntityName>
    <ReferencedEntityName>Contact</ReferencedEntityName>
    <CascadeAssign>Cascade</CascadeAssign>
    <CascadeDelete>Cascade</CascadeDelete>
    <CascadeReparent>Cascade</CascadeReparent>
    <CascadeShare>Cascade</CascadeShare>
    <CascadeUnshare>Cascade</CascadeUnshare>
    <CascadeRollupView>NoCascade</CascadeRollupView>
    <IsValidForAdvancedFind>1</IsValidForAdvancedFind>
    <ReferencingAttributeName>dfeta_PersonId</ReferencingAttributeName>
    <RelationshipDescription>
      <Descriptions>
        <Description description="Unique identifier for Person associated with Employment." languagecode="1033" />
      </Descriptions>
    </RelationshipDescription>
    <EntityRelationshipRoles>
      <EntityRelationshipRole>
        <NavPaneDisplayOption>UseCollectionName</NavPaneDisplayOption>
        <NavPaneArea>Details</NavPaneArea>
        <NavPaneOrder>10000</NavPaneOrder>
        <NavigationPropertyName>dfeta_personid</NavigationPropertyName>
        <CustomLabels>
          <CustomLabel description="" languagecode="1033" />
        </CustomLabels>
        <RelationshipRoleType>1</RelationshipRoleType>
      </EntityRelationshipRole>
      <EntityRelationshipRole>
        <NavigationPropertyName>dfeta_contact_dfeta_employment</NavigationPropertyName>
        <RelationshipRoleType>0</RelationshipRoleType>
      </EntityRelationshipRole>
    </EntityRelationshipRoles>
  </EntityRelationship>
  <EntityRelationship Name="dfeta_contact_dfeta_induction">
    <EntityRelationshipType>OneToMany</EntityRelationshipType>
    <IsCustomizable>1</IsCustomizable>
    <IntroducedVersion>1.5.1.57</IntroducedVersion>
    <IsHierarchical>0</IsHierarchical>
    <ReferencingEntityName>dfeta_induction</ReferencingEntityName>
    <ReferencedEntityName>Contact</ReferencedEntityName>
    <CascadeAssign>Cascade</CascadeAssign>
    <CascadeDelete>Cascade</CascadeDelete>
    <CascadeReparent>Cascade</CascadeReparent>
    <CascadeShare>Cascade</CascadeShare>
    <CascadeUnshare>Cascade</CascadeUnshare>
    <CascadeRollupView>NoCascade</CascadeRollupView>
    <IsValidForAdvancedFind>1</IsValidForAdvancedFind>
    <ReferencingAttributeName>dfeta_PersonId</ReferencingAttributeName>
    <RelationshipDescription>
      <Descriptions>
        <Description description="Unique identifier for Person associated with Induction." languagecode="1033" />
      </Descriptions>
    </RelationshipDescription>
    <EntityRelationshipRoles>
      <EntityRelationshipRole>
        <NavPaneDisplayOption>UseCollectionName</NavPaneDisplayOption>
        <NavPaneArea>Details</NavPaneArea>
        <NavPaneOrder>10000</NavPaneOrder>
        <NavigationPropertyName>dfeta_personid</NavigationPropertyName>
        <CustomLabels>
          <CustomLabel description="" languagecode="1033" />
        </CustomLabels>
        <RelationshipRoleType>1</RelationshipRoleType>
      </EntityRelationshipRole>
      <EntityRelationshipRole>
        <NavigationPropertyName>dfeta_contact_dfeta_induction</NavigationPropertyName>
        <RelationshipRoleType>0</RelationshipRoleType>
      </EntityRelationshipRole>
    </EntityRelationshipRoles>
  </EntityRelationship>
  <EntityRelationship Name="dfeta_contact_dfeta_induction1">
    <EntityRelationshipType>OneToMany</EntityRelationshipType>
    <IsCustomizable>1</IsCustomizable>
    <IntroducedVersion>1.5.1.57</IntroducedVersion>
    <IsHierarchical>0</IsHierarchical>
    <ReferencingEntityName>dfeta_induction</ReferencingEntityName>
    <ReferencedEntityName>Contact</ReferencedEntityName>
    <CascadeAssign>NoCascade</CascadeAssign>
    <CascadeDelete>Restrict</CascadeDelete>
    <CascadeReparent>NoCascade</CascadeReparent>
    <CascadeShare>NoCascade</CascadeShare>
    <CascadeUnshare>NoCascade</CascadeUnshare>
    <CascadeRollupView>NoCascade</CascadeRollupView>
    <IsValidForAdvancedFind>1</IsValidForAdvancedFind>
    <ReferencingAttributeName>dfeta_RequestedById</ReferencingAttributeName>
    <RelationshipDescription>
      <Descriptions>
        <Description description="Unique identifier for Person associated with Induction." languagecode="1033" />
      </Descriptions>
    </RelationshipDescription>
    <EntityRelationshipRoles>
      <EntityRelationshipRole>
        <NavPaneDisplayOption>DoNotDisplay</NavPaneDisplayOption>
        <NavigationPropertyName>dfeta_requestedbyid</NavigationPropertyName>
        <CustomLabels>
          <CustomLabel description="" languagecode="1033" />
        </CustomLabels>
        <RelationshipRoleType>1</RelationshipRoleType>
      </EntityRelationshipRole>
      <EntityRelationshipRole>
        <NavigationPropertyName>dfeta_contact_dfeta_induction1</NavigationPropertyName>
        <RelationshipRoleType>0</RelationshipRoleType>
      </EntityRelationshipRole>
    </EntityRelationshipRoles>
  </EntityRelationship>
  <EntityRelationship Name="dfeta_contact_dfeta_inductionperiod">
    <EntityRelationshipType>OneToMany</EntityRelationshipType>
    <IsCustomizable>1</IsCustomizable>
    <IntroducedVersion>1.5.1.57</IntroducedVersion>
    <IsHierarchical>0</IsHierarchical>
    <ReferencingEntityName>dfeta_inductionperiod</ReferencingEntityName>
    <ReferencedEntityName>Contact</ReferencedEntityName>
    <CascadeAssign>NoCascade</CascadeAssign>
    <CascadeDelete>RemoveLink</CascadeDelete>
    <CascadeReparent>NoCascade</CascadeReparent>
    <CascadeShare>NoCascade</CascadeShare>
    <CascadeUnshare>NoCascade</CascadeUnshare>
    <CascadeRollupView>NoCascade</CascadeRollupView>
    <IsValidForAdvancedFind>1</IsValidForAdvancedFind>
    <ReferencingAttributeName>dfeta_PersonId</ReferencingAttributeName>
    <RelationshipDescription>
      <Descriptions>
        <Description description="Unique identifier for Person associated with Induction Period." languagecode="1033" />
      </Descriptions>
    </RelationshipDescription>
    <EntityRelationshipRoles>
      <EntityRelationshipRole>
        <NavPaneDisplayOption>UseCollectionName</NavPaneDisplayOption>
        <NavPaneArea>Details</NavPaneArea>
        <NavPaneOrder>10000</NavPaneOrder>
        <NavigationPropertyName>dfeta_personid</NavigationPropertyName>
        <CustomLabels>
          <CustomLabel description="" languagecode="1033" />
        </CustomLabels>
        <RelationshipRoleType>1</RelationshipRoleType>
      </EntityRelationshipRole>
      <EntityRelationshipRole>
        <NavigationPropertyName>dfeta_contact_dfeta_inductionperiod</NavigationPropertyName>
        <RelationshipRoleType>0</RelationshipRoleType>
      </EntityRelationshipRole>
    </EntityRelationshipRoles>
  </EntityRelationship>
  <EntityRelationship Name="dfeta_contact_dfeta_initialteachertraining">
    <EntityRelationshipType>OneToMany</EntityRelationshipType>
    <IsCustomizable>1</IsCustomizable>
    <IntroducedVersion>1.5.1.57</IntroducedVersion>
    <IsHierarchical>0</IsHierarchical>
    <ReferencingEntityName>dfeta_initialteachertraining</ReferencingEntityName>
    <ReferencedEntityName>Contact</ReferencedEntityName>
    <CascadeAssign>Cascade</CascadeAssign>
    <CascadeDelete>Cascade</CascadeDelete>
    <CascadeReparent>Cascade</CascadeReparent>
    <CascadeShare>Cascade</CascadeShare>
    <CascadeUnshare>Cascade</CascadeUnshare>
    <CascadeRollupView>NoCascade</CascadeRollupView>
    <IsValidForAdvancedFind>1</IsValidForAdvancedFind>
    <ReferencingAttributeName>dfeta_PersonId</ReferencingAttributeName>
    <RelationshipDescription>
      <Descriptions>
        <Description description="Unique identifier for Person associated with Initial Teacher Training." languagecode="1033" />
      </Descriptions>
    </RelationshipDescription>
    <EntityRelationshipRoles>
      <EntityRelationshipRole>
        <NavPaneDisplayOption>UseCollectionName</NavPaneDisplayOption>
        <NavPaneArea>Details</NavPaneArea>
        <NavPaneOrder>10000</NavPaneOrder>
        <NavigationPropertyName>dfeta_personid</NavigationPropertyName>
        <CustomLabels>
          <CustomLabel description="" languagecode="1033" />
        </CustomLabels>
        <RelationshipRoleType>1</RelationshipRoleType>
      </EntityRelationshipRole>
      <EntityRelationshipRole>
        <NavigationPropertyName>dfeta_contact_dfeta_initialteachertraining</NavigationPropertyName>
        <RelationshipRoleType>0</RelationshipRoleType>
      </EntityRelationshipRole>
    </EntityRelationshipRoles>
  </EntityRelationship>
  <EntityRelationship Name="dfeta_contact_dfeta_initialteachertraining1">
    <EntityRelationshipType>OneToMany</EntityRelationshipType>
    <IsCustomizable>1</IsCustomizable>
    <IntroducedVersion>1.5.1.57</IntroducedVersion>
    <IsHierarchical>0</IsHierarchical>
    <ReferencingEntityName>dfeta_initialteachertraining</ReferencingEntityName>
    <ReferencedEntityName>Contact</ReferencedEntityName>
    <CascadeAssign>NoCascade</CascadeAssign>
    <CascadeDelete>Restrict</CascadeDelete>
    <CascadeReparent>NoCascade</CascadeReparent>
    <CascadeShare>NoCascade</CascadeShare>
    <CascadeUnshare>NoCascade</CascadeUnshare>
    <CascadeRollupView>NoCascade</CascadeRollupView>
    <IsValidForAdvancedFind>1</IsValidForAdvancedFind>
    <ReferencingAttributeName>dfeta_RequestedById</ReferencingAttributeName>
    <RelationshipDescription>
      <Descriptions>
        <Description description="Unique identifier for Person associated with Initial Teacher Training." languagecode="1033" />
      </Descriptions>
    </RelationshipDescription>
    <EntityRelationshipRoles>
      <EntityRelationshipRole>
        <NavPaneDisplayOption>DoNotDisplay</NavPaneDisplayOption>
        <NavPaneArea>Details</NavPaneArea>
        <NavPaneOrder>10000</NavPaneOrder>
        <NavigationPropertyName>dfeta_requestedbyid</NavigationPropertyName>
        <CustomLabels>
          <CustomLabel description="" languagecode="1033" />
        </CustomLabels>
        <RelationshipRoleType>1</RelationshipRoleType>
      </EntityRelationshipRole>
      <EntityRelationshipRole>
        <NavigationPropertyName>dfeta_contact_dfeta_initialteachertraining1</NavigationPropertyName>
        <RelationshipRoleType>0</RelationshipRoleType>
      </EntityRelationshipRole>
    </EntityRelationshipRoles>
  </EntityRelationship>
  <EntityRelationship Name="dfeta_contact_dfeta_integrationtransaction">
    <EntityRelationshipType>OneToMany</EntityRelationshipType>
    <IsCustomizable>1</IsCustomizable>
    <IntroducedVersion>1.5.1.57</IntroducedVersion>
    <IsHierarchical>0</IsHierarchical>
    <ReferencingEntityName>dfeta_integrationtransaction</ReferencingEntityName>
    <ReferencedEntityName>Contact</ReferencedEntityName>
    <CascadeAssign>NoCascade</CascadeAssign>
    <CascadeDelete>RemoveLink</CascadeDelete>
    <CascadeReparent>NoCascade</CascadeReparent>
    <CascadeShare>NoCascade</CascadeShare>
    <CascadeUnshare>NoCascade</CascadeUnshare>
    <CascadeRollupView>NoCascade</CascadeRollupView>
    <IsValidForAdvancedFind>1</IsValidForAdvancedFind>
    <ReferencingAttributeName>dfeta_ImportUser</ReferencingAttributeName>
    <RelationshipDescription>
      <Descriptions>
        <Description description="Unique identifier for Person associated with Integration Transaction." languagecode="1033" />
      </Descriptions>
    </RelationshipDescription>
    <EntityRelationshipRoles>
      <EntityRelationshipRole>
        <NavPaneDisplayOption>DoNotDisplay</NavPaneDisplayOption>
        <NavigationPropertyName>dfeta_importuser</NavigationPropertyName>
        <CustomLabels>
          <CustomLabel description="" languagecode="1033" />
        </CustomLabels>
        <RelationshipRoleType>1</RelationshipRoleType>
      </EntityRelationshipRole>
      <EntityRelationshipRole>
        <NavigationPropertyName>dfeta_contact_dfeta_integrationtransaction</NavigationPropertyName>
        <RelationshipRoleType>0</RelationshipRoleType>
      </EntityRelationshipRole>
    </EntityRelationshipRoles>
  </EntityRelationship>
  <EntityRelationship Name="dfeta_contact_dfeta_integrationtransactionrecor">
    <EntityRelationshipType>OneToMany</EntityRelationshipType>
    <IsCustomizable>1</IsCustomizable>
    <IntroducedVersion>1.5.1.57</IntroducedVersion>
    <IsHierarchical>0</IsHierarchical>
    <ReferencingEntityName>dfeta_integrationtransactionrecord</ReferencingEntityName>
    <ReferencedEntityName>Contact</ReferencedEntityName>
    <CascadeAssign>NoCascade</CascadeAssign>
    <CascadeDelete>RemoveLink</CascadeDelete>
    <CascadeReparent>NoCascade</CascadeReparent>
    <CascadeShare>NoCascade</CascadeShare>
    <CascadeUnshare>NoCascade</CascadeUnshare>
    <CascadeRollupView>NoCascade</CascadeRollupView>
    <IsValidForAdvancedFind>1</IsValidForAdvancedFind>
    <ReferencingAttributeName>dfeta_PersonId</ReferencingAttributeName>
    <RelationshipDescription>
      <Descriptions>
        <Description description="Unique identifier for Person associated with Integration Transaction Record." languagecode="1033" />
      </Descriptions>
    </RelationshipDescription>
    <EntityRelationshipRoles>
      <EntityRelationshipRole>
        <NavPaneDisplayOption>DoNotDisplay</NavPaneDisplayOption>
        <NavPaneArea>Details</NavPaneArea>
        <NavPaneOrder>10000</NavPaneOrder>
        <NavigationPropertyName>dfeta_personid</NavigationPropertyName>
        <CustomLabels>
          <CustomLabel description="" languagecode="1033" />
        </CustomLabels>
        <RelationshipRoleType>1</RelationshipRoleType>
      </EntityRelationshipRole>
      <EntityRelationshipRole>
        <NavigationPropertyName>dfeta_contact_dfeta_integrationtransactionrecor</NavigationPropertyName>
        <RelationshipRoleType>0</RelationshipRoleType>
      </EntityRelationshipRole>
    </EntityRelationshipRoles>
  </EntityRelationship>
  <EntityRelationship Name="dfeta_contact_dfeta_mrapplication">
    <EntityRelationshipType>OneToMany</EntityRelationshipType>
    <IsCustomizable>1</IsCustomizable>
    <IntroducedVersion>1.5.1.57</IntroducedVersion>
    <IsHierarchical>0</IsHierarchical>
    <ReferencingEntityName>dfeta_mrapplication</ReferencingEntityName>
    <ReferencedEntityName>Contact</ReferencedEntityName>
    <CascadeAssign>Cascade</CascadeAssign>
    <CascadeDelete>Cascade</CascadeDelete>
    <CascadeReparent>Cascade</CascadeReparent>
    <CascadeShare>Cascade</CascadeShare>
    <CascadeUnshare>Cascade</CascadeUnshare>
    <CascadeRollupView>NoCascade</CascadeRollupView>
    <IsValidForAdvancedFind>1</IsValidForAdvancedFind>
    <ReferencingAttributeName>dfeta_PersonId</ReferencingAttributeName>
    <RelationshipDescription>
      <Descriptions>
        <Description description="Unique identifier for Person associated with MR Application." languagecode="1033" />
      </Descriptions>
    </RelationshipDescription>
    <EntityRelationshipRoles>
      <EntityRelationshipRole>
        <NavPaneDisplayOption>UseCollectionName</NavPaneDisplayOption>
        <NavPaneArea>Details</NavPaneArea>
        <NavPaneOrder>10000</NavPaneOrder>
        <NavigationPropertyName>dfeta_personid</NavigationPropertyName>
        <CustomLabels>
          <CustomLabel description="" languagecode="1033" />
        </CustomLabels>
        <RelationshipRoleType>1</RelationshipRoleType>
      </EntityRelationshipRole>
      <EntityRelationshipRole>
        <NavigationPropertyName>dfeta_contact_dfeta_mrapplication</NavigationPropertyName>
        <RelationshipRoleType>0</RelationshipRoleType>
      </EntityRelationshipRole>
    </EntityRelationshipRoles>
  </EntityRelationship>
  <EntityRelationship Name="dfeta_contact_dfeta_previousname">
    <EntityRelationshipType>OneToMany</EntityRelationshipType>
    <IsCustomizable>1</IsCustomizable>
    <IntroducedVersion>1.5.1.57</IntroducedVersion>
    <IsHierarchical>0</IsHierarchical>
    <ReferencingEntityName>dfeta_previousname</ReferencingEntityName>
    <ReferencedEntityName>Contact</ReferencedEntityName>
    <CascadeAssign>Cascade</CascadeAssign>
    <CascadeDelete>Cascade</CascadeDelete>
    <CascadeReparent>Cascade</CascadeReparent>
    <CascadeShare>Cascade</CascadeShare>
    <CascadeUnshare>Cascade</CascadeUnshare>
    <CascadeRollupView>NoCascade</CascadeRollupView>
    <IsValidForAdvancedFind>1</IsValidForAdvancedFind>
    <ReferencingAttributeName>dfeta_PersonId</ReferencingAttributeName>
    <RelationshipDescription>
      <Descriptions>
        <Description description="Unique identifier for Person associated with Previous Name." languagecode="1033" />
      </Descriptions>
    </RelationshipDescription>
    <EntityRelationshipRoles>
      <EntityRelationshipRole>
        <NavPaneDisplayOption>UseCollectionName</NavPaneDisplayOption>
        <NavPaneArea>Details</NavPaneArea>
        <NavPaneOrder>10000</NavPaneOrder>
        <NavigationPropertyName>dfeta_personid</NavigationPropertyName>
        <CustomLabels>
          <CustomLabel description="" languagecode="1033" />
        </CustomLabels>
        <RelationshipRoleType>1</RelationshipRoleType>
      </EntityRelationshipRole>
      <EntityRelationshipRole>
        <NavigationPropertyName>dfeta_contact_dfeta_previousname</NavigationPropertyName>
        <RelationshipRoleType>0</RelationshipRoleType>
      </EntityRelationshipRole>
    </EntityRelationshipRoles>
  </EntityRelationship>
  <EntityRelationship Name="dfeta_contact_dfeta_profileamendrequest">
    <EntityRelationshipType>OneToMany</EntityRelationshipType>
    <IsCustomizable>1</IsCustomizable>
    <IntroducedVersion>1.5.1.57</IntroducedVersion>
    <IsHierarchical>0</IsHierarchical>
    <ReferencingEntityName>dfeta_profileamendrequest</ReferencingEntityName>
    <ReferencedEntityName>Contact</ReferencedEntityName>
    <CascadeAssign>Cascade</CascadeAssign>
    <CascadeDelete>Cascade</CascadeDelete>
    <CascadeReparent>Cascade</CascadeReparent>
    <CascadeShare>Cascade</CascadeShare>
    <CascadeUnshare>Cascade</CascadeUnshare>
    <CascadeRollupView>NoCascade</CascadeRollupView>
    <IsValidForAdvancedFind>1</IsValidForAdvancedFind>
    <ReferencingAttributeName>dfeta_RequestedById</ReferencingAttributeName>
    <RelationshipDescription>
      <Descriptions>
        <Description description="Unique identifier for Person associated with Profile Amend Request." languagecode="1033" />
      </Descriptions>
    </RelationshipDescription>
    <EntityRelationshipRoles>
      <EntityRelationshipRole>
        <NavPaneDisplayOption>UseCollectionName</NavPaneDisplayOption>
        <NavPaneArea>Details</NavPaneArea>
        <NavPaneOrder>10000</NavPaneOrder>
        <NavigationPropertyName>dfeta_requestedbyid</NavigationPropertyName>
        <CustomLabels>
          <CustomLabel description="" languagecode="1033" />
        </CustomLabels>
        <RelationshipRoleType>1</RelationshipRoleType>
      </EntityRelationshipRole>
      <EntityRelationshipRole>
        <NavigationPropertyName>dfeta_contact_dfeta_profileamendrequest</NavigationPropertyName>
        <RelationshipRoleType>0</RelationshipRoleType>
      </EntityRelationshipRole>
    </EntityRelationshipRoles>
  </EntityRelationship>
  <EntityRelationship Name="dfeta_contact_dfeta_qtsregistration">
    <EntityRelationshipType>OneToMany</EntityRelationshipType>
    <IsCustomizable>1</IsCustomizable>
    <IntroducedVersion>1.5.1.57</IntroducedVersion>
    <IsHierarchical>0</IsHierarchical>
    <ReferencingEntityName>dfeta_qtsregistration</ReferencingEntityName>
    <ReferencedEntityName>Contact</ReferencedEntityName>
    <CascadeAssign>Cascade</CascadeAssign>
    <CascadeDelete>Cascade</CascadeDelete>
    <CascadeReparent>Cascade</CascadeReparent>
    <CascadeShare>Cascade</CascadeShare>
    <CascadeUnshare>Cascade</CascadeUnshare>
    <CascadeRollupView>NoCascade</CascadeRollupView>
    <IsValidForAdvancedFind>1</IsValidForAdvancedFind>
    <ReferencingAttributeName>dfeta_PersonId</ReferencingAttributeName>
    <RelationshipDescription>
      <Descriptions>
        <Description description="Unique identifier for Person associated with QTS Registration." languagecode="1033" />
      </Descriptions>
    </RelationshipDescription>
    <EntityRelationshipRoles>
      <EntityRelationshipRole>
        <NavPaneDisplayOption>UseCollectionName</NavPaneDisplayOption>
        <NavPaneArea>Details</NavPaneArea>
        <NavPaneOrder>10000</NavPaneOrder>
        <NavigationPropertyName>dfeta_personid</NavigationPropertyName>
        <CustomLabels>
          <CustomLabel description="" languagecode="1033" />
        </CustomLabels>
        <RelationshipRoleType>1</RelationshipRoleType>
      </EntityRelationshipRole>
      <EntityRelationshipRole>
        <NavigationPropertyName>dfeta_contact_dfeta_qtsregistration</NavigationPropertyName>
        <RelationshipRoleType>0</RelationshipRoleType>
      </EntityRelationshipRole>
    </EntityRelationshipRoles>
  </EntityRelationship>
  <EntityRelationship Name="dfeta_contact_dfeta_qtsregistration1">
    <EntityRelationshipType>OneToMany</EntityRelationshipType>
    <IsCustomizable>1</IsCustomizable>
    <IntroducedVersion>1.5.1.57</IntroducedVersion>
    <IsHierarchical>0</IsHierarchical>
    <ReferencingEntityName>dfeta_qtsregistration</ReferencingEntityName>
    <ReferencedEntityName>Contact</ReferencedEntityName>
    <CascadeAssign>NoCascade</CascadeAssign>
    <CascadeDelete>Restrict</CascadeDelete>
    <CascadeReparent>NoCascade</CascadeReparent>
    <CascadeShare>NoCascade</CascadeShare>
    <CascadeUnshare>NoCascade</CascadeUnshare>
    <CascadeRollupView>NoCascade</CascadeRollupView>
    <IsValidForAdvancedFind>1</IsValidForAdvancedFind>
    <ReferencingAttributeName>dfeta_RequestedById</ReferencingAttributeName>
    <RelationshipDescription>
      <Descriptions>
        <Description description="Unique identifier for Person associated with QTS." languagecode="1033" />
      </Descriptions>
    </RelationshipDescription>
    <EntityRelationshipRoles>
      <EntityRelationshipRole>
        <NavPaneDisplayOption>DoNotDisplay</NavPaneDisplayOption>
        <NavigationPropertyName>dfeta_requestedbyid</NavigationPropertyName>
        <CustomLabels>
          <CustomLabel description="" languagecode="1033" />
        </CustomLabels>
        <RelationshipRoleType>1</RelationshipRoleType>
      </EntityRelationshipRole>
      <EntityRelationshipRole>
        <NavigationPropertyName>dfeta_contact_dfeta_qtsregistration1</NavigationPropertyName>
        <RelationshipRoleType>0</RelationshipRoleType>
      </EntityRelationshipRole>
    </EntityRelationshipRoles>
  </EntityRelationship>
  <EntityRelationship Name="dfeta_contact_dfeta_qualification">
    <EntityRelationshipType>OneToMany</EntityRelationshipType>
    <IsCustomizable>1</IsCustomizable>
    <IntroducedVersion>1.5.1.57</IntroducedVersion>
    <IsHierarchical>0</IsHierarchical>
    <ReferencingEntityName>dfeta_qualification</ReferencingEntityName>
    <ReferencedEntityName>Contact</ReferencedEntityName>
    <CascadeAssign>Cascade</CascadeAssign>
    <CascadeDelete>Cascade</CascadeDelete>
    <CascadeReparent>Cascade</CascadeReparent>
    <CascadeShare>Cascade</CascadeShare>
    <CascadeUnshare>Cascade</CascadeUnshare>
    <CascadeRollupView>NoCascade</CascadeRollupView>
    <IsValidForAdvancedFind>1</IsValidForAdvancedFind>
    <ReferencingAttributeName>dfeta_PersonId</ReferencingAttributeName>
    <RelationshipDescription>
      <Descriptions>
        <Description description="Unique identifier for Person associated with Qualification." languagecode="1033" />
      </Descriptions>
    </RelationshipDescription>
    <EntityRelationshipRoles>
      <EntityRelationshipRole>
        <NavPaneDisplayOption>UseCollectionName</NavPaneDisplayOption>
        <NavPaneArea>Details</NavPaneArea>
        <NavPaneOrder>10000</NavPaneOrder>
        <NavigationPropertyName>dfeta_personid</NavigationPropertyName>
        <CustomLabels>
          <CustomLabel description="" languagecode="1033" />
        </CustomLabels>
        <RelationshipRoleType>1</RelationshipRoleType>
      </EntityRelationshipRole>
      <EntityRelationshipRole>
        <NavigationPropertyName>dfeta_contact_dfeta_qualification</NavigationPropertyName>
        <RelationshipRoleType>0</RelationshipRoleType>
      </EntityRelationshipRole>
    </EntityRelationshipRoles>
  </EntityRelationship>
  <EntityRelationship Name="dfeta_contact_dfeta_sanction">
    <EntityRelationshipType>OneToMany</EntityRelationshipType>
    <IsCustomizable>1</IsCustomizable>
    <IntroducedVersion>1.5.1.57</IntroducedVersion>
    <IsHierarchical>0</IsHierarchical>
    <ReferencingEntityName>dfeta_sanction</ReferencingEntityName>
    <ReferencedEntityName>Contact</ReferencedEntityName>
    <CascadeAssign>Cascade</CascadeAssign>
    <CascadeDelete>Cascade</CascadeDelete>
    <CascadeReparent>Cascade</CascadeReparent>
    <CascadeShare>Cascade</CascadeShare>
    <CascadeUnshare>Cascade</CascadeUnshare>
    <CascadeRollupView>NoCascade</CascadeRollupView>
    <IsValidForAdvancedFind>1</IsValidForAdvancedFind>
    <ReferencingAttributeName>dfeta_PersonId</ReferencingAttributeName>
    <RelationshipDescription>
      <Descriptions>
        <Description description="Unique identifier for Person associated with Sanction." languagecode="1033" />
      </Descriptions>
    </RelationshipDescription>
    <EntityRelationshipRoles>
      <EntityRelationshipRole>
        <NavPaneDisplayOption>UseCollectionName</NavPaneDisplayOption>
        <NavPaneArea>Details</NavPaneArea>
        <NavPaneOrder>10000</NavPaneOrder>
        <NavigationPropertyName>dfeta_personid</NavigationPropertyName>
        <CustomLabels>
          <CustomLabel description="" languagecode="1033" />
        </CustomLabels>
        <RelationshipRoleType>1</RelationshipRoleType>
      </EntityRelationshipRole>
      <EntityRelationshipRole>
        <NavigationPropertyName>dfeta_contact_dfeta_sanction</NavigationPropertyName>
        <RelationshipRoleType>0</RelationshipRoleType>
      </EntityRelationshipRole>
    </EntityRelationshipRoles>
  </EntityRelationship>
  <EntityRelationship Name="dfeta_contact_task_potentialduplicateid">
    <EntityRelationshipType>OneToMany</EntityRelationshipType>
    <IsCustomizable>1</IsCustomizable>
    <IntroducedVersion>1.0</IntroducedVersion>
    <IsHierarchical>0</IsHierarchical>
    <ReferencingEntityName>Task</ReferencingEntityName>
    <ReferencedEntityName>Contact</ReferencedEntityName>
    <CascadeAssign>NoCascade</CascadeAssign>
    <CascadeDelete>RemoveLink</CascadeDelete>
    <CascadeReparent>NoCascade</CascadeReparent>
    <CascadeShare>NoCascade</CascadeShare>
    <CascadeUnshare>NoCascade</CascadeUnshare>
    <CascadeRollupView>NoCascade</CascadeRollupView>
    <IsValidForAdvancedFind>1</IsValidForAdvancedFind>
    <ReferencingAttributeName>dfeta_potentialduplicateid</ReferencingAttributeName>
    <RelationshipDescription>
      <Descriptions>
        <Description description="Unique identifier for Person associated with Task." languagecode="1033" />
      </Descriptions>
    </RelationshipDescription>
    <EntityRelationshipRoles>
      <EntityRelationshipRole>
        <NavPaneDisplayOption>UseCollectionName</NavPaneDisplayOption>
        <NavPaneArea>Details</NavPaneArea>
        <NavPaneOrder>10000</NavPaneOrder>
        <NavigationPropertyName>dfeta_potentialduplicateid_task</NavigationPropertyName>
        <CustomLabels>
          <CustomLabel description="" languagecode="1033" />
        </CustomLabels>
        <RelationshipRoleType>1</RelationshipRoleType>
      </EntityRelationshipRole>
      <EntityRelationshipRole>
        <NavigationPropertyName>dfeta_contact_task_potentialduplicateid</NavigationPropertyName>
        <RelationshipRoleType>0</RelationshipRoleType>
      </EntityRelationshipRole>
    </EntityRelationshipRoles>
  </EntityRelationship>
  <EntityRelationship Name="lead_parent_contact">
    <EntityRelationshipType>OneToMany</EntityRelationshipType>
    <IntroducedVersion>5.0.0.0</IntroducedVersion>
    <IsHierarchical>0</IsHierarchical>
    <ReferencingEntityName>Lead</ReferencingEntityName>
    <ReferencedEntityName>Contact</ReferencedEntityName>
    <CascadeAssign>NoCascade</CascadeAssign>
    <CascadeDelete>RemoveLink</CascadeDelete>
    <CascadeReparent>NoCascade</CascadeReparent>
    <CascadeShare>NoCascade</CascadeShare>
    <CascadeUnshare>NoCascade</CascadeUnshare>
    <CascadeRollupView>NoCascade</CascadeRollupView>
    <ReferencingAttributeName>ParentContactId</ReferencingAttributeName>
    <RelationshipDescription>
      <Descriptions>
        <Description description="Choose a contact to connect this lead to, so that the relationship is visible in reports and analytics." languagecode="1033" />
      </Descriptions>
    </RelationshipDescription>
    <EntityRelationshipRoles>
      <EntityRelationshipRole>
        <NavPaneDisplayOption>UseCollectionName</NavPaneDisplayOption>
        <NavPaneArea>Sales</NavPaneArea>
        <NavPaneOrder>0</NavPaneOrder>
        <NavigationPropertyName>parentcontactid</NavigationPropertyName>
        <RelationshipRoleType>1</RelationshipRoleType>
      </EntityRelationshipRole>
      <EntityRelationshipRole>
        <RelationshipRoleType>0</RelationshipRoleType>
      </EntityRelationshipRole>
    </EntityRelationshipRoles>
  </EntityRelationship>
</EntityRelationships>